django_util_js/__init__.py
django_util_js/views.py
django_util_js-0.0.16.dist-info/METADATA
django_util_js-0.0.16.dist-info/WHEEL
django_util_js-0.0.16.dist-info/top_level.txt
django_util_js-0.0.16.dist-info/RECORD
