Metadata-Version: 2.1
Name: django-util-js
Version: 0.0.16
Summary: django's util in javascript. such as url_for etc.
Home-page: https://github.com/dantezhu/django_util_js
Author: dantezhu
Author-email: dantezhu <zny2008@gmail.com>
License: BSD
Project-URL: Homepage, https://github.com/dantezhu/django_util_js
Platform: any
Requires-Dist: django
